aiapi/__init__.py
aisrv-0.1.dev0.dist-info/AUTHORS
aisrv-0.1.dev0.dist-info/LICENSE
aisrv-0.1.dev0.dist-info/METADATA
aisrv-0.1.dev0.dist-info/WHEEL
aisrv-0.1.dev0.dist-info/top_level.txt
aisrv-0.1.dev0.dist-info/RECORD
