Metadata-Version: 2.1
Name: aisrv
Version: 0.1.dev0
Summary: AI API
Author-email: Jérémie DECOCK <jd.jdhp@gmail.com>
Classifier: Development Status :: 4 - Beta
Classifier: Intended Audience :: Developers
Classifier: Natural Language :: English
Classifier: Operating System :: OS Independent
Classifier: Programming Language :: Python :: 3
Classifier: Topic :: Software Development :: Libraries
Classifier: Topic :: Software Development :: Libraries :: Python Modules
Requires-Python: >=3.8
License-File: LICENSE
License-File: AUTHORS
Requires-Dist: fastapi[standard] ~=0.112.0
Requires-Dist: sqlmodel ~=0.0.21
